pytamp/__init__.py
pytamp/_version.py
pytamp/action/__init__.py
pytamp/action/activity.py
pytamp/action/pick.py
pytamp/action/place.py
pytamp/benchmark/__init__.py
pytamp/benchmark/benchmark.py
pytamp/benchmark/benchmark1.py
pytamp/benchmark/benchmark2.py
pytamp/benchmark/benchmark3.py
pytamp/benchmark/benchmark3_old.py
pytamp/benchmark/benchmark4.py
pytamp/benchmark/test.py
pytamp/benchmark/tmp.py
pytamp/planners/__init__.py
pytamp/planners/cartesian_planner.py
pytamp/planners/planner.py
pytamp/planners/rrt_star_planner.py
pytamp/scene/__init__.py
pytamp/scene/object.py
pytamp/scene/render.py
pytamp/scene/scene.py
pytamp/scene/scene_manager.py
pytamp/search/__init__.py
pytamp/search/mcts.py
pytamp/search/node_data.py
pytamp/search/plan.py
pytamp/search/planner.py
pytamp/search/tmp.py
pytamp/utils/__init__.py
pytamp/utils/heuristic_utils.py
pytamp/utils/sampler.py
pytamp-0.5.1.dist-info/LICENSE
pytamp-0.5.1.dist-info/METADATA
pytamp-0.5.1.dist-info/WHEEL
pytamp-0.5.1.dist-info/eager_resources.txt
pytamp-0.5.1.dist-info/top_level.txt
pytamp-0.5.1.dist-info/RECORD
